{"GlobalPropertiesHash":"gQSUvWk4yn6ZVKbrg/89omP7dmC6jjevfAhYoN0tGew=","FingerprintPatternsHash":"gq3WsqcKBUGTSNle7RKKyXRIwh7M8ccEqOqYvIzoM04=","PropertyOverridesHash":"8ZRc1sGeVrPBx4lD717BgRaQekyh78QKV9SKsdt638U=","InputHashes":["IYqlgrtnBF\u002BDIgGqnXxh6/mb4yDzR2eJy7aR82YB8oE=","3kTVG9b45HJZxowI2p5pB4D2WMrfQR8\u002B3ljgrRy4IWc=","ycUnliRk49nhzsZBF9qQctY91lSkvA1gLmDRzuJRmbs=","KtGG\u002B1AONNKKOerDEShvQs4D5HnzrNRAWTxsIuhQu\u002B8=","Vuu2uQqd19/8cXEEHTAhG199DSrifShhghgvzvxb1vQ=","ZfFsFeNENwSx4q6giI9qEjFeOXbD4RGHKDoehdgiljE=","G9gnG8CPsJt8jh6ZJlZ1n7grlMCyF4ZLgVi\u002BpzxrdsU=","rwDjasBWI4NdMc4AMLg1\u002BZnqrxyLg6AiNrYNP5KABCc=","qazLwiXtiasjcS1GEvizOS9CZir85xOLv81PgiTYOiY=","Tm/iLcYwsLLssF\u002BOBDeqC6vWVNeipiUKPG\u002Brny6WTkU=","qYPUdjjBjdPXAw1u\u002B39vE8hEGFN60cIk\u002B/iPt9SIjpg=","dYY1Ut/SbKRScrLpdaZ6VhjaTEzrED6RpSkpbrvaU3o="],"CachedAssets":{"IYqlgrtnBF\u002BDIgGqnXxh6/mb4yDzR2eJy7aR82YB8oE=":{"Identity":"/Users/shafqat/git/FrameworkQ.Formflow/backend/src/FormDesigner.API/wwwroot/css/designer.css","SourceId":"FormDesigner.API","SourceType":"Discovered","ContentRoot":"/Users/shafqat/git/FrameworkQ.Formflow/backend/src/FormDesigner.API/wwwroot/","BasePath":"/","RelativePath":"css/designer#[.{fingerprint}]?.css","AssetKind":"All","AssetMode":"All","AssetRole":"Primary","AssetMergeBehavior":null,"AssetMergeSource":"","RelatedAsset":null,"AssetTraitName":null,"AssetTraitValue":null,"Fingerprint":"rf38eluzqd","Integrity":"mVp/rffpiKzs1iXoZw0fBuvfV5LAj\u002BVxcw2YZDU52js=","CopyToOutputDirectory":"Never","CopyToPublishDirectory":"PreserveNewest","OriginalItemSpec":"wwwroot/css/designer.css","FileLength":6438,"LastWriteTime":"2025-10-01T20:44:39.1276938+00:00"},"ycUnliRk49nhzsZBF9qQctY91lSkvA1gLmDRzuJRmbs=":{"Identity":"/Users/shafqat/git/FrameworkQ.Formflow/backend/src/FormDesigner.API/wwwroot/css/runtime.css","SourceId":"FormDesigner.API","SourceType":"Discovered","ContentRoot":"/Users/shafqat/git/FrameworkQ.Formflow/backend/src/FormDesigner.API/wwwroot/","BasePath":"/","RelativePath":"css/runtime#[.{fingerprint}]?.css","AssetKind":"All","AssetMode":"All","AssetRole":"Primary","AssetMergeBehavior":null,"AssetMergeSource":"","RelatedAsset":null,"AssetTraitName":null,"AssetTraitValue":null,"Fingerprint":"47q9yqj7b4","Integrity":"IBng\u002BreStty4Z\u002B9TUaASy9ZzsIouU8eS8wnkVE\u002BF5jM=","CopyToOutputDirectory":"Never","CopyToPublishDirectory":"PreserveNewest","OriginalItemSpec":"wwwroot/css/runtime.css","FileLength":8265,"LastWriteTime":"2025-10-01T20:48:04.278941+00:00"},"ZfFsFeNENwSx4q6giI9qEjFeOXbD4RGHKDoehdgiljE=":{"Identity":"/Users/shafqat/git/FrameworkQ.Formflow/backend/src/FormDesigner.API/wwwroot/js/designer.js","SourceId":"FormDesigner.API","SourceType":"Discovered","ContentRoot":"/Users/shafqat/git/FrameworkQ.Formflow/backend/src/FormDesigner.API/wwwroot/","BasePath":"/","RelativePath":"js/designer#[.{fingerprint}]?.js","AssetKind":"All","AssetMode":"All","AssetRole":"Primary","AssetMergeBehavior":null,"AssetMergeSource":"","RelatedAsset":null,"AssetTraitName":null,"AssetTraitValue":null,"Fingerprint":"oyo945rmjm","Integrity":"oM49SySs\u002B8pVS3vYp1bH\u002B296T07mLhGD/N5Vpe8id18=","CopyToOutputDirectory":"Never","CopyToPublishDirectory":"PreserveNewest","OriginalItemSpec":"wwwroot/js/designer.js","FileLength":51916,"LastWriteTime":"2025-10-02T02:53:38.586185+00:00"},"Vuu2uQqd19/8cXEEHTAhG199DSrifShhghgvzvxb1vQ=":{"Identity":"/Users/shafqat/git/FrameworkQ.Formflow/backend/src/FormDesigner.API/wwwroot/index.html","SourceId":"FormDesigner.API","SourceType":"Discovered","ContentRoot":"/Users/shafqat/git/FrameworkQ.Formflow/backend/src/FormDesigner.API/wwwroot/","BasePath":"/","RelativePath":"index#[.{fingerprint}]?.html","AssetKind":"All","AssetMode":"All","AssetRole":"Primary","AssetMergeBehavior":null,"AssetMergeSource":"","RelatedAsset":null,"AssetTraitName":null,"AssetTraitValue":null,"Fingerprint":"qpk9aw7ivf","Integrity":"Houg51Ud4FJsXEFYm2TPeg9tmeq6eSc9OGPZ56fxJZM=","CopyToOutputDirectory":"Never","CopyToPublishDirectory":"PreserveNewest","OriginalItemSpec":"wwwroot/index.html","FileLength":8918,"LastWriteTime":"2025-10-02T03:03:22.3727751+00:00"},"KtGG\u002B1AONNKKOerDEShvQs4D5HnzrNRAWTxsIuhQu\u002B8=":{"Identity":"/Users/shafqat/git/FrameworkQ.Formflow/backend/src/FormDesigner.API/wwwroot/css/widgets-enhanced.css","SourceId":"FormDesigner.API","SourceType":"Discovered","ContentRoot":"/Users/shafqat/git/FrameworkQ.Formflow/backend/src/FormDesigner.API/wwwroot/","BasePath":"/","RelativePath":"css/widgets-enhanced#[.{fingerprint}]?.css","AssetKind":"All","AssetMode":"All","AssetRole":"Primary","AssetMergeBehavior":null,"AssetMergeSource":"","RelatedAsset":null,"AssetTraitName":null,"AssetTraitValue":null,"Fingerprint":"h83p2y5v09","Integrity":"XwkYk\u002BwoM3f3JFPUQ\u002Bq36G9sU1a9pr6CJxHie10S2S4=","CopyToOutputDirectory":"Never","CopyToPublishDirectory":"PreserveNewest","OriginalItemSpec":"wwwroot/css/widgets-enhanced.css","FileLength":3516,"LastWriteTime":"2025-10-02T03:02:41.8030269+00:00"},"3kTVG9b45HJZxowI2p5pB4D2WMrfQR8\u002B3ljgrRy4IWc=":{"Identity":"/Users/shafqat/git/FrameworkQ.Formflow/backend/src/FormDesigner.API/wwwroot/css/enterprise-forms.css","SourceId":"FormDesigner.API","SourceType":"Discovered","ContentRoot":"/Users/shafqat/git/FrameworkQ.Formflow/backend/src/FormDesigner.API/wwwroot/","BasePath":"/","RelativePath":"css/enterprise-forms#[.{fingerprint}]?.css","AssetKind":"All","AssetMode":"All","AssetRole":"Primary","AssetMergeBehavior":null,"AssetMergeSource":"","RelatedAsset":null,"AssetTraitName":null,"AssetTraitValue":null,"Fingerprint":"sc06u608dl","Integrity":"tAKogbTC5OL654yF75nkb2F3xYdWeLuogA\u002Btr4nHhYQ=","CopyToOutputDirectory":"Never","CopyToPublishDirectory":"PreserveNewest","OriginalItemSpec":"wwwroot/css/enterprise-forms.css","FileLength":6165,"LastWriteTime":"2025-10-02T03:01:17.471877+00:00"},"G9gnG8CPsJt8jh6ZJlZ1n7grlMCyF4ZLgVi\u002BpzxrdsU=":{"Identity":"/Users/shafqat/git/FrameworkQ.Formflow/backend/src/FormDesigner.API/wwwroot/js/formula-evaluator.js","SourceId":"FormDesigner.API","SourceType":"Discovered","ContentRoot":"/Users/shafqat/git/FrameworkQ.Formflow/backend/src/FormDesigner.API/wwwroot/","BasePath":"/","RelativePath":"js/formula-evaluator#[.{fingerprint}]?.js","AssetKind":"All","AssetMode":"All","AssetRole":"Primary","AssetMergeBehavior":null,"AssetMergeSource":"","RelatedAsset":null,"AssetTraitName":null,"AssetTraitValue":null,"Fingerprint":"150yzvxv3q","Integrity":"NeSYUQfCi54S1Ec7PtPJ1zBwdCQHBzcOsjCUa3CfvdM=","CopyToOutputDirectory":"Never","CopyToPublishDirectory":"PreserveNewest","OriginalItemSpec":"wwwroot/js/formula-evaluator.js","FileLength":8106,"LastWriteTime":"2025-10-02T02:51:12.2336873+00:00"},"rwDjasBWI4NdMc4AMLg1\u002BZnqrxyLg6AiNrYNP5KABCc=":{"Identity":"/Users/shafqat/git/FrameworkQ.Formflow/backend/src/FormDesigner.API/wwwroot/js/formula-parser.js","SourceId":"FormDesigner.API","SourceType":"Discovered","ContentRoot":"/Users/shafqat/git/FrameworkQ.Formflow/backend/src/FormDesigner.API/wwwroot/","BasePath":"/","RelativePath":"js/formula-parser#[.{fingerprint}]?.js","AssetKind":"All","AssetMode":"All","AssetRole":"Primary","AssetMergeBehavior":null,"AssetMergeSource":"","RelatedAsset":null,"AssetTraitName":null,"AssetTraitValue":null,"Fingerprint":"ohcu40kn4w","Integrity":"vB6l9/ElMlEjZcUdq0IrG48IKZsUUMuIbYsXqMjE9ck=","CopyToOutputDirectory":"Never","CopyToPublishDirectory":"PreserveNewest","OriginalItemSpec":"wwwroot/js/formula-parser.js","FileLength":5042,"LastWriteTime":"2025-10-02T02:50:09.2663744+00:00"},"qazLwiXtiasjcS1GEvizOS9CZir85xOLv81PgiTYOiY=":{"Identity":"/Users/shafqat/git/FrameworkQ.Formflow/backend/src/FormDesigner.API/wwwroot/js/runtime.js","SourceId":"FormDesigner.API","SourceType":"Discovered","ContentRoot":"/Users/shafqat/git/FrameworkQ.Formflow/backend/src/FormDesigner.API/wwwroot/","BasePath":"/","RelativePath":"js/runtime#[.{fingerprint}]?.js","AssetKind":"All","AssetMode":"All","AssetRole":"Primary","AssetMergeBehavior":null,"AssetMergeSource":"","RelatedAsset":null,"AssetTraitName":null,"AssetTraitValue":null,"Fingerprint":"8rvjxwb3v0","Integrity":"hNgv\u002BFnwcW1f\u002ByfBM0d/Yf76qFErXda7ryKKwpNsxn0=","CopyToOutputDirectory":"Never","CopyToPublishDirectory":"PreserveNewest","OriginalItemSpec":"wwwroot/js/runtime.js","FileLength":33344,"LastWriteTime":"2025-10-02T03:19:29.9332353+00:00"},"Tm/iLcYwsLLssF\u002BOBDeqC6vWVNeipiUKPG\u002Brny6WTkU=":{"Identity":"/Users/shafqat/git/FrameworkQ.Formflow/backend/src/FormDesigner.API/wwwroot/runtime.html","SourceId":"FormDesigner.API","SourceType":"Discovered","ContentRoot":"/Users/shafqat/git/FrameworkQ.Formflow/backend/src/FormDesigner.API/wwwroot/","BasePath":"/","RelativePath":"runtime#[.{fingerprint}]?.html","AssetKind":"All","AssetMode":"All","AssetRole":"Primary","AssetMergeBehavior":null,"AssetMergeSource":"","RelatedAsset":null,"AssetTraitName":null,"AssetTraitValue":null,"Fingerprint":"tvy9bk3a7q","Integrity":"2YOAaj8L\u002Bp0Qks1fv\u002BoPPloowP3P4mZO0PjmEYs1HCI=","CopyToOutputDirectory":"Never","CopyToPublishDirectory":"PreserveNewest","OriginalItemSpec":"wwwroot/runtime.html","FileLength":7105,"LastWriteTime":"2025-10-02T03:03:00.4429798+00:00"}},"CachedCopyCandidates":{}}